bpcells/__init__.py
bpcells/version.py
bpcells/cpp.cpython-39-x86_64-linux-gnu.so
bpcells/experimental/matrix.py
bpcells/experimental/_slicing.py
bpcells/experimental/__init__.py
bpcells/experimental/fragments.py
bpcells-cpp/factorization/GLMFactorization.h
bpcells-cpp/factorization/GLMFactorization.cpp
bpcells-cpp/matrixTransforms/Scale.h
bpcells-cpp/matrixTransforms/Pow.cpp
bpcells-cpp/matrixTransforms/Round.h
bpcells-cpp/matrixTransforms/Min.cpp
bpcells-cpp/matrixTransforms/MatrixTransform.h
bpcells-cpp/matrixTransforms/SCTransform.cpp
bpcells-cpp/matrixTransforms/Shift.h
bpcells-cpp/matrixTransforms/Round.cpp
bpcells-cpp/matrixTransforms/Min.h
bpcells-cpp/matrixTransforms/Pow.h
bpcells-cpp/matrixTransforms/LinearResidual.cpp
bpcells-cpp/matrixTransforms/SCTransform.h
bpcells-cpp/matrixTransforms/Shift.cpp
bpcells-cpp/matrixTransforms/Scale.cpp
bpcells-cpp/matrixTransforms/Log1p.cpp
bpcells-cpp/matrixTransforms/LinearResidual.h
bpcells-cpp/matrixTransforms/MatrixTransform.cpp
bpcells-cpp/matrixTransforms/Binarize.cpp
bpcells-cpp/matrixTransforms/Binarize.h
bpcells-cpp/matrixTransforms/Log1p.h
bpcells-cpp/simd/overlaps.h
bpcells-cpp/simd/sctransform.cpp
bpcells-cpp/simd/current_target.h
bpcells-cpp/simd/sctransform.h
bpcells-cpp/simd/dense-multiply.h
bpcells-cpp/simd/transform-inl.h
bpcells-cpp/simd/math.cpp
bpcells-cpp/simd/current_target.cpp
bpcells-cpp/simd/dense-multiply.cpp
bpcells-cpp/simd/math.h
bpcells-cpp/simd/overlaps.cpp
bpcells-cpp/simd/libdivide-inl.h
bpcells-cpp/simd/bp128.h
bpcells-cpp/simd/bp128/for_maxbits.cpp
bpcells-cpp/simd/bp128/bp128-helper-inl.h
bpcells-cpp/simd/bp128/diff_maxbits.cpp
bpcells-cpp/simd/bp128/d1z_unpack.cpp
bpcells-cpp/simd/bp128/diff_pack.cpp
bpcells-cpp/simd/bp128/vanilla_unpack.cpp
bpcells-cpp/simd/bp128/for_unpack.cpp
bpcells-cpp/simd/bp128/d1_pack.cpp
bpcells-cpp/simd/bp128/bp128-Nx128.cpp
bpcells-cpp/simd/bp128/d1z_maxbits.cpp
bpcells-cpp/simd/bp128/for_pack.cpp
bpcells-0.3.0rc2.dist-info/top_level.txt
bpcells-0.3.0rc2.dist-info/RECORD
bpcells-0.3.0rc2.dist-info/METADATA
bpcells-0.3.0rc2.dist-info/WHEEL
