Metadata-Version: 2.1
Name: bpcells
Version: 0.3.0rc2
Summary: BPCells python bindings
Author-email: Ben Parks <bnprks+github@gmail.com>
Project-URL: Homepage, https://github.com/bnprks/BPCells
Project-URL: Bug Tracker, https://github.com/bnprks/BPCells/issues
Classifier: Programming Language :: Python :: 3
Classifier: License :: OSI Approved :: MIT License
Classifier: License :: OSI Approved :: Apache Software License
Classifier: Operating System :: OS Independent
Requires-Python: >=3.8
Requires-Dist: numpy
Requires-Dist: pandas
Requires-Dist: scipy
Provides-Extra: build-docs
Requires-Dist: Sphinx ; extra == 'build-docs'
Requires-Dist: pydata-sphinx-theme ; extra == 'build-docs'
Requires-Dist: jupytext ; extra == 'build-docs'
Requires-Dist: myst-nb ; extra == 'build-docs'
Requires-Dist: myst-parser ; extra == 'build-docs'
Provides-Extra: test
Requires-Dist: pytest ; extra == 'test'
Requires-Dist: scipy ; extra == 'test'
Requires-Dist: h5py ; extra == 'test'
Requires-Dist: anndata ; extra == 'test'
